bbbdl/__main__.py
bbbdl/composer.py
bbbdl/exc.py
bbbdl/resources.py
bbbdl/tracks.py
bbbdl/urlhandler.py
bbbdl-1.3.1.dist-info/LICENSE.txt
bbbdl-1.3.1.dist-info/METADATA
bbbdl-1.3.1.dist-info/WHEEL
bbbdl-1.3.1.dist-info/entry_points.txt
bbbdl-1.3.1.dist-info/RECORD
