Metadata-Version: 2.1
Name: bbbdl
Version: 1.3.1
Summary: A downloader for BigBlueButton meetings
License: EUPL-1.2
Author: Stefano Pigozzi
Author-email: ste.pigozzi@gmail.com
Requires-Python: >=3.8,<4.0
Classifier: License :: OSI Approved :: European Union Public Licence 1.2 (EUPL 1.2)
Classifier: Programming Language :: Python :: 3
Classifier: Programming Language :: Python :: 3.8
Classifier: Programming Language :: Python :: 3.9
Classifier: Programming Language :: Python :: 3.10
Classifier: Programming Language :: Python :: 3.11
Classifier: Programming Language :: Python :: 3.12
Requires-Dist: beautifulsoup4 (>=4.9.3,<5.0.0)
Requires-Dist: click (>=7.1.2,<8.0.0)
Requires-Dist: colorama (>=0.4.4,<0.5.0)
Requires-Dist: ffmpeg-python (>=0.2.0,<0.3.0)
Requires-Dist: lxml (>=4.6.1,<5.0.0)
Requires-Dist: requests (>=2.24.0,<3.0.0)
